kksn/__init__.py
kksn/kksn.py
kksn/kksn_server.exe
kksn/client/Monitor.py
kksn/client/__init__.py
kksn/client/auth.py
kksn/client/utils.py
kksn-1.0.114.dist-info/LICENSE.txt
kksn-1.0.114.dist-info/METADATA
kksn-1.0.114.dist-info/README.md
kksn-1.0.114.dist-info/WHEEL
kksn-1.0.114.dist-info/pyproject.toml
kksn-1.0.114.dist-info/setup.py
kksn-1.0.114.dist-info/top_level.txt
kksn-1.0.114.dist-info/RECORD
