Metadata-Version: 2.2
Name: kksn
Version: 1.0.114
Summary: kksn序列号生成器
Author: Kuizi
Author-email: 123751307@qq.com
License: MIT
Classifier: Development Status :: 3 - Alpha
Classifier: Programming Language :: Python :: 3
Classifier: License :: OSI Approved :: MIT License
Classifier: Operating System :: Microsoft :: Windows
Classifier: Intended Audience :: Developers
Classifier: Topic :: Utilities
Requires-Python: >=3.5
License-File: LICENSE.txt
License-File: README.md
License-File: pyproject.toml
License-File: setup.py
Requires-Dist: wmi
Requires-Dist: ntplib
Dynamic: author
Dynamic: author-email
Dynamic: classifier
Dynamic: description
Dynamic: description-content-type
Dynamic: license
Dynamic: requires-dist
Dynamic: requires-python
Dynamic: summary
